dingtalk_stream/__init__.py
dingtalk_stream/card_callback.py
dingtalk_stream/card_instance.py
dingtalk_stream/card_replier.py
dingtalk_stream/chatbot.py
dingtalk_stream/credential.py
dingtalk_stream/frames.py
dingtalk_stream/graph.py
dingtalk_stream/handlers.py
dingtalk_stream/interactive_card.py
dingtalk_stream/log.py
dingtalk_stream/stream.py
dingtalk_stream/utils.py
dingtalk_stream/version.py
dingtalk_stream-0.24.2.dist-info/LICENSE
dingtalk_stream-0.24.2.dist-info/METADATA
dingtalk_stream-0.24.2.dist-info/WHEEL
dingtalk_stream-0.24.2.dist-info/top_level.txt
dingtalk_stream-0.24.2.dist-info/RECORD
