Metadata-Version: 2.1
Name: dingtalk-stream
Version: 0.24.2
Summary: A Python library for sending messages to DingTalk chatbot
Home-page: https://github.com/open-dingtalk/dingtalk-stream-sdk-python
Author: Ke Jie
Author-email: jinxi.kj@alibaba-inc.com
License: MIT
Classifier: Development Status :: 3 - Alpha
Classifier: Intended Audience :: Developers
Classifier: License :: OSI Approved :: MIT License
Classifier: Programming Language :: Python :: 3
Classifier: Programming Language :: Python :: 3.6
Classifier: Programming Language :: Python :: 3.7
Classifier: Programming Language :: Python :: 3.8
Classifier: Programming Language :: Python :: 3.9
Classifier: Programming Language :: Python :: Implementation :: CPython
Classifier: Programming Language :: Python :: Implementation :: PyPy
License-File: LICENSE
Requires-Dist: aiohttp >=3.10.0
Requires-Dist: requests >=2.27.1
Requires-Dist: websockets >=11.0.2
